testlog/__init__.py
testlog-0.0.1.dist-info/LICENSE
testlog-0.0.1.dist-info/METADATA
testlog-0.0.1.dist-info/WHEEL
testlog-0.0.1.dist-info/top_level.txt
testlog-0.0.1.dist-info/RECORD
