Metadata-Version: 2.1
Name: testlog
Version: 0.0.1
Summary: CompatibL Test Log Library
Home-page: https://github.com/compatibl/testlog
Author: The Project Contributors
License: UNKNOWN
Project-URL: Source Code, https://github.com/compatibl/testlog
Platform: UNKNOWN
Classifier: Development Status :: 3 - Alpha
Classifier: Intended Audience :: Developers
Classifier: Intended Audience :: Science/Research
Classifier: Intended Audience :: Financial and Insurance Industry
Classifier: Topic :: Software Development
Classifier: Topic :: Scientific/Engineering
Classifier: License :: OSI Approved :: Apache Software License
Classifier: Programming Language :: Python :: 3.9
Classifier: Programming Language :: Python :: 3.10
Classifier: Programming Language :: Python :: 3.11
Classifier: Operating System :: OS Independent
License-File: LICENSE
Requires-Dist: pdoc (>=12.0.2)
Requires-Dist: pytest (>=6.1.1)
